pyqt_find_replace_widget/__init__.py
pyqt_find_replace_widget/main.py
pyqt_find_replace_widget-0.0.11.dist-info/LICENSE
pyqt_find_replace_widget-0.0.11.dist-info/METADATA
pyqt_find_replace_widget-0.0.11.dist-info/WHEEL
pyqt_find_replace_widget-0.0.11.dist-info/top_level.txt
pyqt_find_replace_widget-0.0.11.dist-info/RECORD
