Metadata-Version: 2.1
Name: pyqt-find-replace-widget
Version: 0.0.11
Summary: PyQt widget which can find and replace text
Home-page: https://github.com/yjg30737/pyqt-find-replace-widget.git
Author: Jung Gyu Yoon
Author-email: yjg30737@gmail.com
License: MIT
License-File: LICENSE
Requires-Dist: PyQt5 (>=5.8)
